overhang/Overhang.py
overhang/OverhangSet.py
overhang/__init__.py
overhang/reports.py
overhang/tools.py
overhang/report_assets/overhang_report.pug
overhang/report_assets/overhangset_report.pug
overhang/report_assets/report_style.css
overhang-0.1.8.dist-info/licenses/LICENSE
overhang-0.1.8.dist-info/METADATA
overhang-0.1.8.dist-info/WHEEL
overhang-0.1.8.dist-info/top_level.txt
overhang-0.1.8.dist-info/RECORD
