Metadata-Version: 2.4
Name: overhang
Version: 0.1.8
Summary: Compendium of overhangs
Author: Peter Vegh
License-Expression: MIT
Project-URL: Homepage, https://github.com/Edinburgh-Genome-Foundry/overhang
Keywords: biology,overhang,dna
License-File: LICENSE
Requires-Dist: matplotlib
Requires-Dist: minotaor
Requires-Dist: networkx
Requires-Dist: numpy
Requires-Dist: pdf_reports
Requires-Dist: tatapov
Dynamic: license-file
